Metadata-Version: 2.4
Name: llama-index-embeddings-gigachat
Version: 0.4.1
Summary: llama-index embeddings gigachat integration
Author-email: Kirill Kukharev <lepeshokoff200@mail.ru>
License-Expression: MIT
License-File: LICENSE
Requires-Python: <4.0,>=3.9
Requires-Dist: gigachat==0.1.28
Requires-Dist: llama-index-core<0.15,>=0.13.0
